cdk_cloudformation_awscommunity_time_static/__init__.py
cdk_cloudformation_awscommunity_time_static/py.typed
cdk_cloudformation_awscommunity_time_static/_jsii/__init__.py
cdk_cloudformation_awscommunity_time_static/_jsii/awscommunity-time-static@1.8.0-alpha.7.jsii.tgz
cdk_cloudformation_awscommunity_time_static-1.8.0a7.dist-info/LICENSE
cdk_cloudformation_awscommunity_time_static-1.8.0a7.dist-info/METADATA
cdk_cloudformation_awscommunity_time_static-1.8.0a7.dist-info/WHEEL
cdk_cloudformation_awscommunity_time_static-1.8.0a7.dist-info/top_level.txt
cdk_cloudformation_awscommunity_time_static-1.8.0a7.dist-info/RECORD
